hdcms/__init__.py
hdcms/gen.py
hdcms/stats.py
hdcms/verify.py
hdcms/visualize.py
hdcms-0.1.27.dist-info/LICENSE.txt
hdcms-0.1.27.dist-info/METADATA
hdcms-0.1.27.dist-info/WHEEL
hdcms-0.1.27.dist-info/top_level.txt
hdcms-0.1.27.dist-info/RECORD
