Metadata-Version: 2.1
Name: hdcms
Version: 0.1.27
Summary: This package creates useful helper functions for python API
Author: Arun Moorthy
Author-email: Jason Eveleth <hdcms-helper@jasoneveleth.com>
License: NIST-developed software is provided by NIST as a public service. You may use,
Project-URL: Homepage, https://github.com/jasoneveleth/hdcms-python
Project-URL: Bug Tracker, https://github.com/jasoneveleth/hdcms-python/issues
Requires-Python: >=3.7
License-File: LICENSE.txt
Requires-Dist: hdcms-bindings
Requires-Dist: opencv-python
Requires-Dist: numpy
Requires-Dist: matplotlib
Requires-Dist: scipy
